loctraceback/__init__.py
loctraceback/linecache.py
loctraceback/ltraceback.py
loctraceback/version.py
loctraceback-1.1.1.dist-info/DESCRIPTION.rst
loctraceback-1.1.1.dist-info/METADATA
loctraceback-1.1.1.dist-info/RECORD
loctraceback-1.1.1.dist-info/WHEEL
loctraceback-1.1.1.dist-info/metadata.json
loctraceback-1.1.1.dist-info/top_level.txt
loctraceback-1.1.1.dist-info/zip-safe
