Metadata-Version: 2.0
Name: loctraceback
Version: 1.1.1
Summary: traceback with more exact location info
Home-page: https://github.com/rocky/python-loctraceback/
Author: Rocky Bernstein
Author-email: rb@dustyfeet.com
License: GPL-3.0
Platform: UNKNOWN
Classifier: Development Status :: 3 - Alpha
Classifier: Intended Audience :: Developers
Classifier: Operating System :: OS Independent
Classifier: License :: OSI Approved :: Python Software Foundation License
Classifier: Programming Language :: Python
Classifier: Programming Language :: Python :: 3.3
Classifier: Programming Language :: Python :: 3.4
Classifier: Programming Language :: Python :: 3.5
Classifier: Programming Language :: Python :: 3.6
Classifier: Programming Language :: Python :: 3.7
Classifier: Programming Language :: Python :: 3.8
Classifier: Topic :: Software Development :: Debuggers
Classifier: Topic :: Software Development :: Libraries :: Python Modules
Requires-Dist: uncompyle6 (>=3.0.1)
Requires-Dist: xdis (<5.1.0,>=5.0.0)
Requires-Dist: pyficache (>=2.2.1)
